ya_speech_key/__init__.py
ya_speech_key-0.0.2.dist-info/LICENSE.md
ya_speech_key-0.0.2.dist-info/METADATA
ya_speech_key-0.0.2.dist-info/WHEEL
ya_speech_key-0.0.2.dist-info/top_level.txt
ya_speech_key-0.0.2.dist-info/RECORD
