Metadata-Version: 2.1
Name: ya-speech-key
Version: 0.0.2
Summary: Extracts Yandex Speech API key from translate page
Home-page: https://github.com/Aculeasis/ya-speech-key
Author: Aculeasis
Author-email: amilpalimov2@ya.ru
License: MIT
Platform: UNKNOWN
Classifier: Intended Audience :: Developers
Classifier: Programming Language :: Python :: 2.7
Classifier: Programming Language :: Python :: 3.4
Classifier: Programming Language :: Python :: 3.5
Classifier: Programming Language :: Python :: 3.6
Classifier: Programming Language :: Python :: 3.7
Classifier: Operating System :: OS Independent
Classifier: License :: OSI Approved :: MIT License
Classifier: Topic :: Multimedia :: Sound/Audio :: Speech
Classifier: Topic :: Software Development :: Libraries
